{
  "data": [
    {
      "first_name": "Venkateshwara",
      "middle_name": "Swamy",
      "last_name": "Devuda",
      "date_of_birth": "12-12-1992"
    },
    {
      "first_name": "John",
      "middle_name": "Doe",
      "last_name": "Smith",
      "date_of_birth": "01-05-1987"
    },
    {
      "first_name": "Jane",
      "middle_name": "Marie",
      "last_name": "Johnson",
      "date_of_birth": "07-10-1995"
    },
    {
      "first_name": "Michael",
      "middle_name": "James",
      "last_name": "Brown",
      "date_of_birth": "03-20-1980"
    },
    {
      "first_name": "Sarah",
      "middle_name": "Elizabeth",
      "last_name": "Wilson",
      "date_of_birth": "11-14-1976"
    },
    {
      "first_name": "David",
      "middle_name": "Robert",
      "last_name": "Davis",
      "date_of_birth": "09-02-1990"
    },
    {
      "first_name": "Emily",
      "middle_name": "Grace",
      "last_name": "Anderson",
      "date_of_birth": "06-30-1988"
    },
    {
      "first_name": "Christopher",
      "middle_name": "Lee",
      "last_name": "Taylor",
      "date_of_birth": "04-18-1993"
    },
    {
      "first_name": "Emma",
      "middle_name": "Sophia",
      "last_name": "Lee",
      "date_of_birth": "02-12-1998"
    },
    {
      "first_name": "Daniel",
      "middle_name": "Joseph",
      "last_name": "Miller",
      "date_of_birth": "08-25-1985"
    }
  ]
}
